airda/__init__.py
airda/agent/__init__.py
airda/agent/action/__init__.py
airda/agent/action/explainer.py
airda/agent/action/searcher.py
airda/agent/action/sql_generator.py
airda/agent/agent.py
airda/agent/assistants/__init__.py
airda/agent/assistants/assistant_keys.py
airda/agent/assistants/assistant_manager.py
airda/agent/assistants/chat_assistant/__init__.py
airda/agent/assistants/chat_assistant/chat_assistant.py
airda/agent/assistants/chat_assistant/prompt.py
airda/agent/assistants/sql_assistant/__init__.py
airda/agent/assistants/sql_assistant/sql_assistant.py
airda/agent/assistants/sql_assistant/sql_strategy.py
airda/agent/data_agent_context.py
airda/agent/env.py
airda/agent/exception/__init__.py
airda/agent/exception/action_type_error.py
airda/agent/exception/already_exists_error.py
airda/agent/llm/__init__.py
airda/agent/llm/data_agent_llm_keys.py
airda/agent/llm/data_agent_llm_manager.py
airda/agent/llm/openai.py
airda/agent/log/__init__.py
airda/agent/planner/__init__.py
airda/agent/planner/data_agent_pipeline.py
airda/agent/planner/data_agent_planner.py
airda/agent/planner/data_agent_planner_params.py
airda/agent/process_pool/DataAgentProcessPool.py
airda/agent/process_pool/__init__.py
airda/agent/rag/__init__.py
airda/agent/rag/data_agent_rag.py
airda/agent/rag/embedding/__init__.py
airda/agent/rag/embedding/data_agent_embedding_model.py
airda/agent/rag/schema_linking/__init__.py
airda/agent/rag/schema_linking/data_agent_schema_linking.py
airda/agent/storage/__init__.py
airda/agent/storage/entity/__init__.py
airda/agent/storage/entity/colunm_detail.py
airda/agent/storage/entity/datasource.py
airda/agent/storage/entity/instruction.py
airda/agent/storage/repositories/__init__.py
airda/agent/storage/repositories/datasource_repository.py
airda/agent/storage/repositories/instruction_repository.py
airda/agent/storage/repositories/respository.py
airda/agent/storage/storage.py
airda/agent/tools/__init__.py
airda/agent/utils/__init__.py
airda/agent/utils/file.py
airda-0.0.3.dist-info/LICENSE
airda-0.0.3.dist-info/METADATA
airda-0.0.3.dist-info/WHEEL
airda-0.0.3.dist-info/entry_points.txt
airda-0.0.3.dist-info/RECORD
