Metadata-Version: 2.1
Name: airda
Version: 0.0.3
Summary: airda
Author: hitsz-ids
Requires-Python: >=3.10,<4.0
Classifier: Programming Language :: Python :: 3
Classifier: Programming Language :: Python :: 3.10
Classifier: Programming Language :: Python :: 3.11
Classifier: Programming Language :: Python :: 3.12
Requires-Dist: fastapi (==0.99.0)
Requires-Dist: httpx (==0.24.1)
Requires-Dist: jieba (==0.42.1)
Requires-Dist: langchain (==0.1.0)
Requires-Dist: mysql-connector-python (>=8.3.0,<9.0.0)
Requires-Dist: openpyxl (==3.1.2)
Requires-Dist: overrides (==7.4.0)
Requires-Dist: pandas (==2.1.1)
Requires-Dist: prompt-toolkit (>=3.0.43,<4.0.0)
Requires-Dist: pyarmor (==7.7.4)
Requires-Dist: pydantic (==1.10.12)
Requires-Dist: pymongo (>=4.6.2,<5.0.0)
Requires-Dist: python-docx (==0.8.11)
Requires-Dist: python-dotenv (==1.0.0)
Requires-Dist: python-multipart (==0.0.6)
Requires-Dist: pyyaml (>=6.0.1,<7.0.0)
Requires-Dist: scikit-learn (>=1.4.1.post1,<2.0.0)
Requires-Dist: shortuuid (==1.0.11)
Requires-Dist: sql-metadata (==2.8.0)
Requires-Dist: sqlparse (==0.4.4)
Requires-Dist: torch (==2.0.1)
Requires-Dist: transformers (>=4.39.0,<5.0.0)
Requires-Dist: unstructured (==0.10.16)
